{"name": "Jason Puncheon", "events": [{"player": {"name": "Jason Puncheon"}, "time": 43, "matchID": 3267, "season": 2014, "leagueID": 1000, "leaguename": "English Premier League", "type": "goal", "teamFor": "Crystal Palace", "teamAgainst": "Liverpool FC", "venueStatus": "A", "goalType": "free kick", "assistBy": "", "teamForScore": 1, "teamAgainstScore": 1, "gameStatus": "D"}, {"player": {"name": "Jason Puncheon"}, "time": 16, "matchID": 3690, "season": 2012, "leagueID": 1000, "leaguename": "English Premier League", "type": "assist", "teamFor": "Southampton FC", "teamAgainst": "Manchester United", "venueStatus": "H", "goalType": "", "goalBy": "Rickie Lambert", "teamForScore": 1, "teamAgainstScore": 0}, {"player": {"name": "Jason Puncheon"}, "time": 68, "matchID": 2843, "season": 2015, "leagueID": 1000, "leaguename": "English Premier League", "type": "goal", "teamFor": "Crystal Palace", "teamAgainst": "Norwich City", "venueStatus": "H", "goalType": "left-footed shot", "assistBy": "Joel Ward", "teamForScore": 1, "teamAgainstScore": 0, "gameStatus": "W"}, {"player": {"name": "Jason Puncheon"}, "time": 44, "matchID": 3473, "season": 2013, "leagueID": 1000, "leaguename": "English Premier League", "type": "goal", "teamFor": "Crystal Palace", "teamAgainst": "Norwich City", "venueStatus": "H", "goalType": "penalty", "assistBy": "", "teamForScore": 1, "teamAgainstScore": 1, "gameStatus": "D"}, {"player": {"name": "Jason Puncheon"}, "time": 62, "matchID": 4674, "season": 2010, "leagueID": 1000, "leaguename": "English Premier League", "type": "goal", "teamFor": "Blackpool FC", "teamAgainst": "Everton FC", "venueStatus": "A", "goalType": "left-footed shot", "assistBy": "James Beattie", "teamForScore": 2, "teamAgainstScore": 2, "gameStatus": "D"}, {"player": {"name": "Jason Puncheon"}, "time": 48, "matchID": 3210, "season": 2014, "leagueID": 1000, "leaguename": "English Premier League", "type": "goal", "teamFor": "Crystal Palace", "teamAgainst": "Manchester City", "venueStatus": "H", "goalType": "free kick", "assistBy": "", "teamForScore": 2, "teamAgainstScore": 0, "gameStatus": "W+"}, {"player": {"name": "Jason Puncheon"}, "time": 71, "matchID": 2542, "season": 2015, "leagueID": 1000, "leaguename": "English Premier League", "type": "assist", "teamFor": "Crystal Palace", "teamAgainst": "Aston Villa", "venueStatus": "H", "goalType": "header", "goalBy": "Scott Dann", "teamForScore": 1, "teamAgainstScore": 0}, {"player": {"name": "Jason Puncheon"}, "time": 85, "matchID": 2272, "season": 2016, "leagueID": 1000, "leaguename": "English Premier League", "type": "assist", "teamFor": "Crystal Palace", "teamAgainst": "Southampton FC", "venueStatus": "H", "goalType": "right-footed shot", "goalBy": "Christian Benteke", "teamForScore": 3, "teamAgainstScore": 0}, {"player": {"name": "Jason Puncheon"}, "time": 7, "matchID": 3917, "season": 2012, "leagueID": 1000, "leaguename": "English Premier League", "type": "goal", "teamFor": "Southampton FC", "teamAgainst": "Manchester City", "venueStatus": "H", "goalType": "", "assistBy": "", "teamForScore": 1, "teamAgainstScore": 0, "gameStatus": "W"}, {"player": {"name": "Jason Puncheon"}, "time": 45, "matchID": 3775, "season": 2012, "leagueID": 1000, "leaguename": "English Premier League", "type": "goal", "teamFor": "Southampton FC", "teamAgainst": "Queens Park Rangers", "venueStatus": "A", "goalType": "", "assistBy": "Nathaniel Clyne", "teamForScore": 2, "teamAgainstScore": 0, "gameStatus": "W+"}, {"player": {"name": "Jason Puncheon"}, "time": 34, "matchID": 2508, "season": 2016, "leagueID": 1000, "leaguename": "English Premier League", "type": "assist", "teamFor": "Crystal Palace", "teamAgainst": "Hull City", "venueStatus": "H", "goalType": "header", "goalBy": "Christian Benteke", "teamForScore": 2, "teamAgainstScore": 0}, {"player": {"name": "Jason Puncheon"}, "time": 74, "matchID": 2476, "season": 2016, "leagueID": 1000, "leaguename": "English Premier League", "type": "assist", "teamFor": "Crystal Palace", "teamAgainst": "Liverpool FC", "venueStatus": "A", "goalType": "header", "goalBy": "Christian Benteke", "teamForScore": 2, "teamAgainstScore": 1}, {"player": {"name": "Jason Puncheon"}, "time": 23, "matchID": 3539, "season": 2013, "leagueID": 1000, "leaguename": "English Premier League", "type": "goal", "teamFor": "Crystal Palace", "teamAgainst": "Everton FC", "venueStatus": "A", "goalType": "left-footed shot", "assistBy": "Marouane Chamakh", "teamForScore": 1, "teamAgainstScore": 0, "gameStatus": "W"}, {"player": {"name": "Jason Puncheon"}, "time": 73, "matchID": 3539, "season": 2013, "leagueID": 1000, "leaguename": "English Premier League", "type": "assist", "teamFor": "Crystal Palace", "teamAgainst": "Everton FC", "venueStatus": "A", "goalType": "right-footed shot", "goalBy": "Cameron Jerome", "teamForScore": 3, "teamAgainstScore": 1}, {"player": {"name": "Jason Puncheon"}, "time": 31, "matchID": 3603, "season": 2013, "leagueID": 1000, "leaguename": "English Premier League", "type": "goal", "teamFor": "Crystal Palace", "teamAgainst": "Cardiff City", "venueStatus": "A", "goalType": "", "assistBy": "Joe Ledley", "teamForScore": 1, "teamAgainstScore": 0, "gameStatus": "W"}, {"player": {"name": "Jason Puncheon"}, "time": 88, "matchID": 3603, "season": 2013, "leagueID": 1000, "leaguename": "English Premier League", "type": "goal", "teamFor": "Crystal Palace", "teamAgainst": "Cardiff City", "venueStatus": "A", "goalType": "", "assistBy": "Adrian Mariappa", "teamForScore": 3, "teamAgainstScore": 0, "gameStatus": "W+"}, {"player": {"name": "Jason Puncheon"}, "time": 19, "matchID": 4781, "season": 2010, "leagueID": 1000, "leaguename": "English Premier League", "type": "goal", "teamFor": "Blackpool FC", "teamAgainst": "Bolton Wanderers", "venueStatus": "H", "goalType": "left-footed shot", "assistBy": "Gary Taylor-Fletcher", "teamForScore": 2, "teamAgainstScore": 1, "gameStatus": "W"}, {"player": {"name": "Jason Puncheon"}, "time": 76, "matchID": 4027, "season": 2012, "leagueID": 1000, "leaguename": "English Premier League", "type": "goal", "teamFor": "Southampton FC", "teamAgainst": "Sunderland AFC", "venueStatus": "A", "goalType": "", "assistBy": "", "teamForScore": 1, "teamAgainstScore": 1, "gameStatus": "D"}, {"player": {"name": "Jason Puncheon"}, "time": 6, "matchID": 3422, "season": 2013, "leagueID": 1000, "leaguename": "English Premier League", "type": "assist", "teamFor": "Crystal Palace", "teamAgainst": "Cardiff City", "venueStatus": "H", "goalType": "", "goalBy": "Cameron Jerome", "teamForScore": 1, "teamAgainstScore": 0}, {"player": {"name": "Jason Puncheon"}, "time": 54, "matchID": 2953, "season": 2014, "leagueID": 1000, "leaguename": "English Premier League", "type": "assist", "teamFor": "Crystal Palace", "teamAgainst": "Leicester City", "venueStatus": "H", "goalType": "", "goalBy": "Mile Jedinak", "teamForScore": 2, "teamAgainstScore": 0}, {"player": {"name": "Jason Puncheon"}, "time": 48, "matchID": 3112, "season": 2014, "leagueID": 1000, "leaguename": "English Premier League", "type": "goal", "teamFor": "Crystal Palace", "teamAgainst": "Burnley FC", "venueStatus": "A", "goalType": "right-footed shot", "assistBy": "Dwight Gayle", "teamForScore": 2, "teamAgainstScore": 2, "gameStatus": "D"}, {"player": {"name": "Jason Puncheon"}, "time": 87, "matchID": 3112, "season": 2014, "leagueID": 1000, "leaguename": "English Premier League", "type": "assist", "teamFor": "Crystal Palace", "teamAgainst": "Burnley FC", "venueStatus": "A", "goalType": "left-footed shot", "goalBy": "Dwight Gayle", "teamForScore": 3, "teamAgainstScore": 2}, {"player": {"name": "Jason Puncheon"}, "time": 35, "matchID": 2907, "season": 2014, "leagueID": 1000, "leaguename": "English Premier League", "type": "assist", "teamFor": "Crystal Palace", "teamAgainst": "Arsenal FC", "venueStatus": "A", "goalType": "header", "goalBy": "Brede Hangeland", "teamForScore": 1, "teamAgainstScore": 0}, {"player": {"name": "Jason Puncheon"}, "time": 41, "matchID": 3161, "season": 2014, "leagueID": 1000, "leaguename": "English Premier League", "type": "assist", "teamFor": "Crystal Palace", "teamAgainst": "West Ham United", "venueStatus": "A", "goalType": "header", "goalBy": "Glenn Murray", "teamForScore": 1, "teamAgainstScore": 0}, {"player": {"name": "Jason Puncheon"}, "time": 51, "matchID": 3161, "season": 2014, "leagueID": 1000, "leaguename": "English Premier League", "type": "assist", "teamFor": "Crystal Palace", "teamAgainst": "West Ham United", "venueStatus": "A", "goalType": "header", "goalBy": "Scott Dann", "teamForScore": 2, "teamAgainstScore": 0}, {"player": {"name": "Jason Puncheon"}, "time": 63, "matchID": 3161, "season": 2014, "leagueID": 1000, "leaguename": "English Premier League", "type": "assist", "teamFor": "Crystal Palace", "teamAgainst": "West Ham United", "venueStatus": "A", "goalType": "header", "goalBy": "Glenn Murray", "teamForScore": 3, "teamAgainstScore": 0}, {"player": {"name": "Jason Puncheon"}, "time": 64, "matchID": 2895, "season": 2015, "leagueID": 1000, "leaguename": "English Premier League", "type": "goal", "teamFor": "Crystal Palace", "teamAgainst": "Southampton FC", "venueStatus": "A", "goalType": "left-footed shot", "assistBy": "", "teamForScore": 1, "teamAgainstScore": 2, "gameStatus": "L"}, {"player": {"name": "Jason Puncheon"}, "time": 86, "matchID": 4710, "season": 2010, "leagueID": 1000, "leaguename": "English Premier League", "type": "goal", "teamFor": "Blackpool FC", "teamAgainst": "Chelsea FC", "venueStatus": "H", "goalType": "left-footed shot", "assistBy": "Matt Phillips", "teamForScore": 1, "teamAgainstScore": 3, "gameStatus": "L"}, {"player": {"name": "Jason Puncheon"}, "time": 48, "matchID": 2923, "season": 2014, "leagueID": 1000, "leaguename": "English Premier League", "type": "goal", "teamFor": "Crystal Palace", "teamAgainst": "Newcastle United", "venueStatus": "A", "goalType": "left-footed shot", "assistBy": "Yannick Bolasie", "teamForScore": 2, "teamAgainstScore": 1, "gameStatus": "W"}, {"player": {"name": "Jason Puncheon"}, "time": 76, "matchID": 3611, "season": 2013, "leagueID": 1000, "leaguename": "English Premier League", "type": "goal", "teamFor": "Crystal Palace", "teamAgainst": "Aston Villa", "venueStatus": "H", "goalType": "", "assistBy": "Yannick Bolasie", "teamForScore": 1, "teamAgainstScore": 0, "gameStatus": "W"}, {"player": {"name": "Jason Puncheon"}, "time": 80, "matchID": 3108, "season": 2014, "leagueID": 1000, "leaguename": "English Premier League", "type": "goal", "teamFor": "Crystal Palace", "teamAgainst": "Tottenham Hotspur", "venueStatus": "H", "goalType": "left-footed shot", "assistBy": "", "teamForScore": 2, "teamAgainstScore": 1, "gameStatus": "W"}, {"player": {"name": "Jason Puncheon"}, "time": 76, "matchID": 2670, "season": 2015, "leagueID": 1000, "leaguename": "English Premier League", "type": "assist", "teamFor": "Crystal Palace", "teamAgainst": "Everton FC", "venueStatus": "A", "goalType": "header", "goalBy": "Scott Dann", "teamForScore": 1, "teamAgainstScore": 0}, {"player": {"name": "Jason Puncheon"}, "time": 57, "matchID": 3257, "season": 2014, "leagueID": 1000, "leaguename": "English Premier League", "type": "goal", "teamFor": "Crystal Palace", "teamAgainst": "Manchester United", "venueStatus": "H", "goalType": "free kick", "assistBy": "", "teamForScore": 1, "teamAgainstScore": 1, "gameStatus": "D"}, {"player": {"name": "Jason Puncheon"}, "time": 39, "matchID": 2525, "season": 2015, "leagueID": 1000, "leaguename": "English Premier League", "type": "assist", "teamFor": "Crystal Palace", "teamAgainst": "Norwich City", "venueStatus": "A", "goalType": "right-footed shot", "goalBy": "Wilfried Zaha", "teamForScore": 1, "teamAgainstScore": 0}, {"player": {"name": "Jason Puncheon"}, "time": 69, "matchID": 2949, "season": 2014, "leagueID": 1000, "leaguename": "English Premier League", "type": "assist", "teamFor": "Crystal Palace", "teamAgainst": "Everton FC", "venueStatus": "A", "goalType": "right-footed shot", "goalBy": "Yannick Bolasie", "teamForScore": 3, "teamAgainstScore": 1}, {"player": {"name": "Jason Puncheon"}, "time": 11, "matchID": 2188, "season": 2016, "leagueID": 1000, "leaguename": "English Premier League", "type": "assist", "teamFor": "Crystal Palace", "teamAgainst": "Stoke City", "venueStatus": "H", "goalType": "header", "goalBy": "Scott Dann", "teamForScore": 2, "teamAgainstScore": 0}, {"player": {"name": "Jason Puncheon"}, "time": 61, "matchID": 3813, "season": 2012, "leagueID": 1000, "leaguename": "English Premier League", "type": "goal", "teamFor": "Southampton FC", "teamAgainst": "Reading FC", "venueStatus": "H", "goalType": "", "assistBy": "Nathaniel Clyne", "teamForScore": 1, "teamAgainstScore": 0, "gameStatus": "W"}, {"player": {"name": "Jason Puncheon"}, "time": 51, "matchID": 3496, "season": 2013, "leagueID": 1000, "leaguename": "English Premier League", "type": "goal", "teamFor": "Crystal Palace", "teamAgainst": "Stoke City", "venueStatus": "H", "goalType": "", "assistBy": "", "teamForScore": 1, "teamAgainstScore": 0, "gameStatus": "W"}, {"player": {"name": "Jason Puncheon"}, "time": 16, "matchID": 3505, "season": 2013, "leagueID": 1000, "leaguename": "English Premier League", "type": "goal", "teamFor": "Crystal Palace", "teamAgainst": "Hull City", "venueStatus": "H", "goalType": "", "assistBy": "Marouane Chamakh", "teamForScore": 1, "teamAgainstScore": 0, "gameStatus": "W"}, {"player": {"name": "Jason Puncheon"}, "time": 35, "matchID": 3867, "season": 2012, "leagueID": 1000, "leaguename": "English Premier League", "type": "assist", "teamFor": "Southampton FC", "teamAgainst": "Arsenal FC", "venueStatus": "H", "goalType": "right-footed shot", "goalBy": "Gast\u00f3n Ram\u00edrez", "teamForScore": 1, "teamAgainstScore": 0}, {"player": {"name": "Jason Puncheon"}, "time": 75, "matchID": 3830, "season": 2012, "leagueID": 1000, "leaguename": "English Premier League", "type": "goal", "teamFor": "Southampton FC", "teamAgainst": "Chelsea FC", "venueStatus": "A", "goalType": "", "assistBy": "", "teamForScore": 2, "teamAgainstScore": 2, "gameStatus": "D"}, {"player": {"name": "Jason Puncheon"}, "time": 90, "matchID": 2163, "season": 2016, "leagueID": 1000, "leaguename": "English Premier League", "type": "assist", "teamFor": "Crystal Palace", "teamAgainst": "AFC Bournemouth", "venueStatus": "H", "goalType": "header", "goalBy": "Scott Dann", "teamForScore": 1, "teamAgainstScore": 1}], "id": 1330, "clubStats": [{"club": "Crystal Palace", "goals": 15, "owngoals": 0, "penalties": 1, "assists": 17, "gcGoal": 12, "gcAssists": 0, "homeGoals": 8, "awayGoals": 7, "pointsWon": 48, "appearances": 132, "subappearances": 0, "minsPlayed": 11643, "appearancesHome": 66, "appearancesAway": 66, "subappearancesHome": 12, "subappearancesAway": 9, "minsPlayedHome": 5780, "minsPlayedAway": 5863}, {"club": "Southampton FC", "goals": 5, "owngoals": 0, "penalties": 0, "assists": 2, "gcGoal": 4, "gcAssists": 0, "homeGoals": 2, "awayGoals": 3, "pointsWon": 15, "appearances": 25, "subappearances": 0, "minsPlayed": 2067, "appearancesHome": 14, "appearancesAway": 11, "subappearancesHome": 2, "subappearancesAway": 5, "minsPlayedHome": 1134, "minsPlayedAway": 933}, {"club": "Blackpool FC", "goals": 3, "owngoals": 0, "penalties": 0, "assists": 0, "gcGoal": 2, "gcAssists": 0, "homeGoals": 2, "awayGoals": 1, "pointsWon": 0, "appearances": 6, "subappearances": 0, "minsPlayed": 648, "appearancesHome": 3, "appearancesAway": 3, "subappearancesHome": 3, "subappearancesAway": 2, "minsPlayedHome": 342, "minsPlayedAway": 306}, {"club": "Queens Park Rangers", "goals": 0, "owngoals": 0, "penalties": 0, "assists": 0, "gcGoal": 0, "gcAssists": 0, "homeGoals": 0, "awayGoals": 0, "pointsWon": 0, "appearances": 0, "subappearances": 0, "minsPlayed": 15, "appearancesHome": 0, "appearancesAway": 0, "subappearancesHome": 2, "subappearancesAway": 0, "minsPlayedHome": 15, "minsPlayedAway": 0}, {"club": "Huddersfield Town", "goals": 0, "owngoals": 0, "penalties": 0, "assists": 0, "gcGoal": 0, "gcAssists": 0, "homeGoals": 0, "awayGoals": 0, "pointsWon": 0, "appearances": 5, "subappearances": 0, "minsPlayed": 383, "appearancesHome": 3, "appearancesAway": 2, "subappearancesHome": 0, "subappearancesAway": 1, "minsPlayedHome": 246, "minsPlayedAway": 137}]}