{"name": "Nicklas Bendtner", "events": [{"player": {"name": "Nicklas Bendtner"}, "time": 86, "matchID": 5397, "season": 2008, "leagueID": 1000, "leaguename": "English Premier League", "type": "goal", "teamFor": "Arsenal FC", "teamAgainst": "Hull City", "venueStatus": "A", "goalType": "", "assistBy": "Robin van Persie", "teamForScore": 3, "teamAgainstScore": 1, "gameStatus": "W+"}, {"player": {"name": "Nicklas Bendtner"}, "time": 8, "matchID": 4599, "season": 2010, "leagueID": 1000, "leaguename": "English Premier League", "type": "assist", "teamFor": "Arsenal FC", "teamAgainst": "Stoke City", "venueStatus": "H", "goalType": "header", "goalBy": "S\u00e9bastien Squillaci", "teamForScore": 1, "teamAgainstScore": 0}, {"player": {"name": "Nicklas Bendtner"}, "time": 36, "matchID": 4393, "season": 2011, "leagueID": 1000, "leaguename": "English Premier League", "type": "goal", "teamFor": "Sunderland AFC", "teamAgainst": "Bolton Wanderers", "venueStatus": "H", "goalType": "", "assistBy": "Jack Colback", "teamForScore": 1, "teamAgainstScore": 1, "gameStatus": "D"}, {"player": {"name": "Nicklas Bendtner"}, "time": 70, "matchID": 5539, "season": 2008, "leagueID": 1000, "leaguename": "English Premier League", "type": "goal", "teamFor": "Arsenal FC", "teamAgainst": "Chelsea FC", "venueStatus": "H", "goalType": "header", "assistBy": "Bacary Sagna", "teamForScore": 1, "teamAgainstScore": 3, "gameStatus": "L"}, {"player": {"name": "Nicklas Bendtner"}, "time": 26, "matchID": 5225, "season": 2008, "leagueID": 1000, "leaguename": "English Premier League", "type": "assist", "teamFor": "Arsenal FC", "teamAgainst": "Bolton Wanderers", "venueStatus": "A", "goalType": "right-footed shot", "goalBy": "Emmanuel Ebou\u00e9", "teamForScore": 1, "teamAgainstScore": 1}, {"player": {"name": "Nicklas Bendtner"}, "time": 27, "matchID": 5225, "season": 2008, "leagueID": 1000, "leaguename": "English Premier League", "type": "goal", "teamFor": "Arsenal FC", "teamAgainst": "Bolton Wanderers", "venueStatus": "A", "goalType": "right-footed shot", "assistBy": "Denilson", "teamForScore": 2, "teamAgainstScore": 1, "gameStatus": "W"}, {"player": {"name": "Nicklas Bendtner"}, "time": 80, "matchID": 5792, "season": 2007, "leagueID": 1000, "leaguename": "English Premier League", "type": "assist", "teamFor": "Arsenal FC", "teamAgainst": "Newcastle United", "venueStatus": "H", "goalType": "left-footed shot", "goalBy": "Cesc F\u00e0bregas", "teamForScore": 3, "teamAgainstScore": 0}, {"player": {"name": "Nicklas Bendtner"}, "time": 58, "matchID": 5758, "season": 2007, "leagueID": 1000, "leaguename": "English Premier League", "type": "assist", "teamFor": "Arsenal FC", "teamAgainst": "Everton FC", "venueStatus": "A", "goalType": "left-footed shot", "goalBy": "Eduardo", "teamForScore": 2, "teamAgainstScore": 1}, {"player": {"name": "Nicklas Bendtner"}, "time": 14, "matchID": 5097, "season": 2009, "leagueID": 1000, "leaguename": "English Premier League", "type": "assist", "teamFor": "Arsenal FC", "teamAgainst": "Hull City", "venueStatus": "A", "goalType": "right-footed shot", "goalBy": "Andrey Arshavin", "teamForScore": 1, "teamAgainstScore": 0}, {"player": {"name": "Nicklas Bendtner"}, "time": 90, "matchID": 5097, "season": 2009, "leagueID": 1000, "leaguename": "English Premier League", "type": "goal", "teamFor": "Arsenal FC", "teamAgainst": "Hull City", "venueStatus": "A", "goalType": "right-footed shot", "assistBy": "Denilson", "teamForScore": 2, "teamAgainstScore": 1, "gameStatus": "W"}, {"player": {"name": "Nicklas Bendtner"}, "time": 57, "matchID": 5477, "season": 2008, "leagueID": 1000, "leaguename": "English Premier League", "type": "goal", "teamFor": "Arsenal FC", "teamAgainst": "Newcastle United", "venueStatus": "A", "goalType": "header", "assistBy": "Andrey Arshavin", "teamForScore": 1, "teamAgainstScore": 0, "gameStatus": "W"}, {"player": {"name": "Nicklas Bendtner"}, "time": 76, "matchID": 5928, "season": 2007, "leagueID": 1000, "leaguename": "English Premier League", "type": "goal", "teamFor": "Arsenal FC", "teamAgainst": "Everton FC", "venueStatus": "H", "goalType": "header", "assistBy": "Armand Traor\u00e9", "teamForScore": 1, "teamAgainstScore": 0, "gameStatus": "W"}, {"player": {"name": "Nicklas Bendtner"}, "time": 4, "matchID": 5452, "season": 2008, "leagueID": 1000, "leaguename": "English Premier League", "type": "goal", "teamFor": "Arsenal FC", "teamAgainst": "West Bromwich Albion", "venueStatus": "A", "goalType": "", "assistBy": "Denilson", "teamForScore": 1, "teamAgainstScore": 0, "gameStatus": "W"}, {"player": {"name": "Nicklas Bendtner"}, "time": 44, "matchID": 5452, "season": 2008, "leagueID": 1000, "leaguename": "English Premier League", "type": "goal", "teamFor": "Arsenal FC", "teamAgainst": "West Bromwich Albion", "venueStatus": "A", "goalType": "", "assistBy": "Kolo Tour\u00e9", "teamForScore": 3, "teamAgainstScore": 1, "gameStatus": "W+"}, {"player": {"name": "Nicklas Bendtner"}, "time": 27, "matchID": 5062, "season": 2009, "leagueID": 1000, "leaguename": "English Premier League", "type": "goal", "teamFor": "Arsenal FC", "teamAgainst": "Sunderland AFC", "venueStatus": "H", "goalType": "right-footed shot", "assistBy": "Emmanuel Ebou\u00e9", "teamForScore": 1, "teamAgainstScore": 0, "gameStatus": "W"}, {"player": {"name": "Nicklas Bendtner"}, "time": 19, "matchID": 4206, "season": 2011, "leagueID": 1000, "leaguename": "English Premier League", "type": "goal", "teamFor": "Sunderland AFC", "teamAgainst": "Queens Park Rangers", "venueStatus": "A", "goalType": "", "assistBy": "Kieran Richardson", "teamForScore": 1, "teamAgainstScore": 0, "gameStatus": "W"}, {"player": {"name": "Nicklas Bendtner"}, "time": 5, "matchID": 5107, "season": 2009, "leagueID": 1000, "leaguename": "English Premier League", "type": "assist", "teamFor": "Arsenal FC", "teamAgainst": "West Ham United", "venueStatus": "H", "goalType": "right-footed shot", "goalBy": "Denilson", "teamForScore": 1, "teamAgainstScore": 0}, {"player": {"name": "Nicklas Bendtner"}, "time": 90, "matchID": 5269, "season": 2008, "leagueID": 1000, "leaguename": "English Premier League", "type": "assist", "teamFor": "Arsenal FC", "teamAgainst": "West Ham United", "venueStatus": "A", "goalType": "right-footed shot", "goalBy": "Emmanuel Adebayor", "teamForScore": 2, "teamAgainstScore": 0}, {"player": {"name": "Nicklas Bendtner"}, "time": 41, "matchID": 4336, "season": 2011, "leagueID": 1000, "leaguename": "English Premier League", "type": "goal", "teamFor": "Sunderland AFC", "teamAgainst": "Queens Park Rangers", "venueStatus": "H", "goalType": "", "assistBy": "James McClean", "teamForScore": 1, "teamAgainstScore": 0, "gameStatus": "W"}, {"player": {"name": "Nicklas Bendtner"}, "time": 90, "matchID": 4852, "season": 2009, "leagueID": 1000, "leaguename": "English Premier League", "type": "assist", "teamFor": "Arsenal FC", "teamAgainst": "Wigan Athletic", "venueStatus": "H", "goalType": "right-footed shot", "goalBy": "Cesc F\u00e0bregas", "teamForScore": 4, "teamAgainstScore": 0}, {"player": {"name": "Nicklas Bendtner"}, "time": 90, "matchID": 5122, "season": 2009, "leagueID": 1000, "leaguename": "English Premier League", "type": "goal", "teamFor": "Arsenal FC", "teamAgainst": "Wolverhampton Wanderers", "venueStatus": "H", "goalType": "header", "assistBy": "Bacary Sagna", "teamForScore": 1, "teamAgainstScore": 0, "gameStatus": "W"}, {"player": {"name": "Nicklas Bendtner"}, "time": 90, "matchID": 4123, "season": 2011, "leagueID": 1000, "leaguename": "English Premier League", "type": "goal", "teamFor": "Sunderland AFC", "teamAgainst": "Bolton Wanderers", "venueStatus": "A", "goalType": "", "assistBy": "St\u00e9phane Sess\u00e8gnon", "teamForScore": 2, "teamAgainstScore": 0, "gameStatus": "W+"}, {"player": {"name": "Nicklas Bendtner"}, "time": 60, "matchID": 5081, "season": 2009, "leagueID": 1000, "leaguename": "English Premier League", "type": "assist", "teamFor": "Arsenal FC", "teamAgainst": "Burnley FC", "venueStatus": "H", "goalType": "left-footed shot", "goalBy": "Theo Walcott", "teamForScore": 2, "teamAgainstScore": 1}, {"player": {"name": "Nicklas Bendtner"}, "time": 88, "matchID": 3472, "season": 2013, "leagueID": 1000, "leaguename": "English Premier League", "type": "goal", "teamFor": "Arsenal FC", "teamAgainst": "Cardiff City", "venueStatus": "H", "goalType": "right-footed shot", "assistBy": "", "teamForScore": 1, "teamAgainstScore": 0, "gameStatus": "W"}, {"player": {"name": "Nicklas Bendtner"}, "time": 85, "matchID": 5692, "season": 2007, "leagueID": 1000, "leaguename": "English Premier League", "type": "assist", "teamFor": "Arsenal FC", "teamAgainst": "Wigan Athletic", "venueStatus": "H", "goalType": "right-footed shot", "goalBy": "Tom\u00e1\u0161 Rosick\u00fd", "teamForScore": 2, "teamAgainstScore": 0}, {"player": {"name": "Nicklas Bendtner"}, "time": 84, "matchID": 5382, "season": 2008, "leagueID": 1000, "leaguename": "English Premier League", "type": "goal", "teamFor": "Arsenal FC", "teamAgainst": "Bolton Wanderers", "venueStatus": "H", "goalType": "right-footed shot", "assistBy": "Robin van Persie", "teamForScore": 1, "teamAgainstScore": 0, "gameStatus": "W"}, {"player": {"name": "Nicklas Bendtner"}, "time": 85, "matchID": 5140, "season": 2009, "leagueID": 1000, "leaguename": "English Premier League", "type": "goal", "teamFor": "Arsenal FC", "teamAgainst": "Tottenham Hotspur", "venueStatus": "A", "goalType": "right-footed shot", "assistBy": "Theo Walcott", "teamForScore": 1, "teamAgainstScore": 2, "gameStatus": "L"}, {"player": {"name": "Nicklas Bendtner"}, "time": 13, "matchID": 5524, "season": 2008, "leagueID": 1000, "leaguename": "English Premier League", "type": "goal", "teamFor": "Arsenal FC", "teamAgainst": "Portsmouth FC", "venueStatus": "A", "goalType": "header", "assistBy": "Andrey Arshavin", "teamForScore": 1, "teamAgainstScore": 0, "gameStatus": "W"}, {"player": {"name": "Nicklas Bendtner"}, "time": 41, "matchID": 5524, "season": 2008, "leagueID": 1000, "leaguename": "English Premier League", "type": "goal", "teamFor": "Arsenal FC", "teamAgainst": "Portsmouth FC", "venueStatus": "A", "goalType": "penalty", "assistBy": "", "teamForScore": 2, "teamAgainstScore": 0, "gameStatus": "W+"}, {"player": {"name": "Nicklas Bendtner"}, "time": 28, "matchID": 4089, "season": 2011, "leagueID": 1000, "leaguename": "English Premier League", "type": "assist", "teamFor": "Sunderland AFC", "teamAgainst": "Stoke City", "venueStatus": "H", "goalType": "", "goalBy": "Craig Gardner", "teamForScore": 3, "teamAgainstScore": 0}, {"player": {"name": "Nicklas Bendtner"}, "time": 89, "matchID": 4876, "season": 2009, "leagueID": 1000, "leaguename": "English Premier League", "type": "goal", "teamFor": "Arsenal FC", "teamAgainst": "Blackburn Rovers", "venueStatus": "H", "goalType": "right-footed shot", "assistBy": "Aaron Ramsey", "teamForScore": 6, "teamAgainstScore": 2, "gameStatus": "W+"}, {"player": {"name": "Nicklas Bendtner"}, "time": 24, "matchID": 4105, "season": 2011, "leagueID": 1000, "leaguename": "English Premier League", "type": "goal", "teamFor": "Sunderland AFC", "teamAgainst": "West Bromwich Albion", "venueStatus": "H", "goalType": "", "assistBy": "Sebastian Larsson", "teamForScore": 1, "teamAgainstScore": 2, "gameStatus": "L"}, {"player": {"name": "Nicklas Bendtner"}, "time": 27, "matchID": 4105, "season": 2011, "leagueID": 1000, "leaguename": "English Premier League", "type": "assist", "teamFor": "Sunderland AFC", "teamAgainst": "West Bromwich Albion", "venueStatus": "H", "goalType": "", "goalBy": "Ahmed Elmohamady", "teamForScore": 2, "teamAgainstScore": 2}, {"player": {"name": "Nicklas Bendtner"}, "time": 76, "matchID": 5731, "season": 2007, "leagueID": 1000, "leaguename": "English Premier League", "type": "goal", "teamFor": "Arsenal FC", "teamAgainst": "Tottenham Hotspur", "venueStatus": "H", "goalType": "header", "assistBy": "Cesc F\u00e0bregas", "teamForScore": 2, "teamAgainstScore": 1, "gameStatus": "W"}, {"player": {"name": "Nicklas Bendtner"}, "time": 56, "matchID": 4314, "season": 2011, "leagueID": 1000, "leaguename": "English Premier League", "type": "goal", "teamFor": "Sunderland AFC", "teamAgainst": "Liverpool FC", "venueStatus": "H", "goalType": "", "assistBy": "Fraizer Campbell", "teamForScore": 1, "teamAgainstScore": 0, "gameStatus": "W"}, {"player": {"name": "Nicklas Bendtner"}, "time": 2, "matchID": 3412, "season": 2013, "leagueID": 1000, "leaguename": "English Premier League", "type": "goal", "teamFor": "Arsenal FC", "teamAgainst": "Hull City", "venueStatus": "H", "goalType": "", "assistBy": "Carl Jenkinson", "teamForScore": 1, "teamAgainstScore": 0, "gameStatus": "W"}, {"player": {"name": "Nicklas Bendtner"}, "time": 90, "matchID": 5831, "season": 2007, "leagueID": 1000, "leaguename": "English Premier League", "type": "goal", "teamFor": "Arsenal FC", "teamAgainst": "Aston Villa", "venueStatus": "H", "goalType": "right-footed shot", "assistBy": "Emmanuel Adebayor", "teamForScore": 1, "teamAgainstScore": 1, "gameStatus": "D"}, {"player": {"name": "Nicklas Bendtner"}, "time": 25, "matchID": 5920, "season": 2007, "leagueID": 1000, "leaguename": "English Premier League", "type": "goal", "teamFor": "Arsenal FC", "teamAgainst": "Derby County", "venueStatus": "A", "goalType": "right-footed shot", "assistBy": "Robin van Persie", "teamForScore": 1, "teamAgainstScore": 0, "gameStatus": "W"}, {"player": {"name": "Nicklas Bendtner"}, "time": 54, "matchID": 5881, "season": 2007, "leagueID": 1000, "leaguename": "English Premier League", "type": "goal", "teamFor": "Arsenal FC", "teamAgainst": "Liverpool FC", "venueStatus": "H", "goalType": "header", "assistBy": "Cesc F\u00e0bregas", "teamForScore": 1, "teamAgainstScore": 1, "gameStatus": "D"}, {"player": {"name": "Nicklas Bendtner"}, "time": 88, "matchID": 4510, "season": 2010, "leagueID": 1000, "leaguename": "English Premier League", "type": "goal", "teamFor": "Arsenal FC", "teamAgainst": "Manchester City", "venueStatus": "A", "goalType": "right-footed shot", "assistBy": "Samir Nasri", "teamForScore": 3, "teamAgainstScore": 0, "gameStatus": "W+"}, {"player": {"name": "Nicklas Bendtner"}, "time": 39, "matchID": 4619, "season": 2010, "leagueID": 1000, "leaguename": "English Premier League", "type": "assist", "teamFor": "Arsenal FC", "teamAgainst": "Wigan Athletic", "venueStatus": "A", "goalType": "right-footed shot", "goalBy": "Andrey Arshavin", "teamForScore": 1, "teamAgainstScore": 1}, {"player": {"name": "Nicklas Bendtner"}, "time": 44, "matchID": 4619, "season": 2010, "leagueID": 1000, "leaguename": "English Premier League", "type": "goal", "teamFor": "Arsenal FC", "teamAgainst": "Wigan Athletic", "venueStatus": "A", "goalType": "right-footed shot", "assistBy": "Andrey Arshavin", "teamForScore": 2, "teamAgainstScore": 1, "gameStatus": "W"}, {"player": {"name": "Nicklas Bendtner"}, "time": 32, "matchID": 5076, "season": 2009, "leagueID": 1000, "leaguename": "English Premier League", "type": "goal", "teamFor": "Arsenal FC", "teamAgainst": "Stoke City", "venueStatus": "A", "goalType": "header", "assistBy": "Cesc F\u00e0bregas", "teamForScore": 1, "teamAgainstScore": 1, "gameStatus": "D"}, {"player": {"name": "Nicklas Bendtner"}, "time": 45, "matchID": 4344, "season": 2011, "leagueID": 1000, "leaguename": "English Premier League", "type": "goal", "teamFor": "Sunderland AFC", "teamAgainst": "Manchester City", "venueStatus": "A", "goalType": "", "assistBy": "St\u00e9phane Sess\u00e8gnon", "teamForScore": 2, "teamAgainstScore": 1, "gameStatus": "W"}, {"player": {"name": "Nicklas Bendtner"}, "time": 55, "matchID": 4344, "season": 2011, "leagueID": 1000, "leaguename": "English Premier League", "type": "assist", "teamFor": "Sunderland AFC", "teamAgainst": "Manchester City", "venueStatus": "A", "goalType": "", "goalBy": "Sebastian Larsson", "teamForScore": 3, "teamAgainstScore": 1}, {"player": {"name": "Nicklas Bendtner"}, "time": 25, "matchID": 4308, "season": 2011, "leagueID": 1000, "leaguename": "English Premier League", "type": "goal", "teamFor": "Sunderland AFC", "teamAgainst": "Newcastle United", "venueStatus": "A", "goalType": "penalty", "assistBy": "Michael Turner", "teamForScore": 1, "teamAgainstScore": 0, "gameStatus": "W"}], "id": 1535, "clubStats": [{"club": "Arsenal FC", "goals": 24, "owngoals": 0, "penalties": 1, "assists": 11, "gcGoal": 17, "gcAssists": 0, "homeGoals": 11, "awayGoals": 13, "pointsWon": 51, "appearances": 41, "subappearances": 0, "minsPlayed": 4595, "appearancesHome": 18, "appearancesAway": 23, "subappearancesHome": 34, "subappearancesAway": 33, "minsPlayedHome": 2047, "minsPlayedAway": 2548}, {"club": "Sunderland AFC", "goals": 8, "owngoals": 0, "penalties": 1, "assists": 3, "gcGoal": 6, "gcAssists": 0, "homeGoals": 4, "awayGoals": 4, "pointsWon": 9, "appearances": 25, "subappearances": 0, "minsPlayed": 2231, "appearancesHome": 14, "appearancesAway": 11, "subappearancesHome": 0, "subappearancesAway": 3, "minsPlayedHome": 1151, "minsPlayedAway": 1080}]}