{"name": "Pierre-Emile H\u00f8jbjerg", "events": [{"player": {"name": "Pierre-Emile H\u00f8jbjerg"}, "time": 35, "matchID": 1430, "season": 2018, "leagueID": 1000, "leaguename": "English Premier League", "type": "goal", "teamFor": "Southampton FC", "teamAgainst": "Brighton & Hove Albion", "venueStatus": "H", "goalType": "right-footed shot", "assistBy": "", "teamForScore": 1, "teamAgainstScore": 0, "gameStatus": "W"}, {"player": {"name": "Pierre-Emile H\u00f8jbjerg"}, "time": 9, "matchID": 1704, "season": 2018, "leagueID": 1000, "leaguename": "English Premier League", "type": "assist", "teamFor": "Southampton FC", "teamAgainst": "Liverpool FC", "venueStatus": "H", "goalType": "right-footed shot", "goalBy": "Shane Long", "teamForScore": 1, "teamAgainstScore": 0}, {"player": {"name": "Pierre-Emile H\u00f8jbjerg"}, "time": 37, "matchID": 1579, "season": 2018, "leagueID": 1000, "leaguename": "English Premier League", "type": "goal", "teamFor": "Southampton FC", "teamAgainst": "Manchester City", "venueStatus": "H", "goalType": "right-footed shot", "assistBy": "", "teamForScore": 1, "teamAgainstScore": 1, "gameStatus": "D"}, {"player": {"name": "Pierre-Emile H\u00f8jbjerg"}, "time": 15, "matchID": 1555, "season": 2018, "leagueID": 1000, "leaguename": "English Premier League", "type": "assist", "teamFor": "Southampton FC", "teamAgainst": "Huddersfield Town", "venueStatus": "A", "goalType": "right-footed shot", "goalBy": "Nathan Redmond", "teamForScore": 1, "teamAgainstScore": 0}, {"player": {"name": "Pierre-Emile H\u00f8jbjerg"}, "time": 31, "matchID": 1184, "season": 2019, "leagueID": 1000, "leaguename": "English Premier League", "type": "assist", "teamFor": "Southampton FC", "teamAgainst": "Chelsea FC", "venueStatus": "A", "goalType": "left-footed shot", "goalBy": "Michael Obafemi", "teamForScore": 1, "teamAgainstScore": 0}, {"player": {"name": "Pierre-Emile H\u00f8jbjerg"}, "time": 90, "matchID": 1414, "season": 2018, "leagueID": 1000, "leaguename": "English Premier League", "type": "goal", "teamFor": "Southampton FC", "teamAgainst": "Crystal Palace", "venueStatus": "A", "goalType": "left-footed shot", "assistBy": "Matt Targett", "teamForScore": 2, "teamAgainstScore": 0, "gameStatus": "W+"}, {"player": {"name": "Pierre-Emile H\u00f8jbjerg"}, "time": 55, "matchID": 1735, "season": 2018, "leagueID": 1000, "leaguename": "English Premier League", "type": "assist", "teamFor": "Southampton FC", "teamAgainst": "AFC Bournemouth", "venueStatus": "H", "goalType": "left-footed shot", "goalBy": "James Ward-Prowse", "teamForScore": 2, "teamAgainstScore": 2}, {"player": {"name": "Pierre-Emile H\u00f8jbjerg"}, "time": 53, "matchID": 1694, "season": 2018, "leagueID": 1000, "leaguename": "English Premier League", "type": "goal", "teamFor": "Southampton FC", "teamAgainst": "Brighton & Hove Albion", "venueStatus": "A", "goalType": "right-footed shot", "assistBy": "Nathan Redmond", "teamForScore": 1, "teamAgainstScore": 0, "gameStatus": "W"}], "id": 1811, "clubStats": [{"club": "Southampton FC", "goals": 4, "owngoals": 0, "penalties": 0, "assists": 4, "gcGoal": 3, "gcAssists": 0, "homeGoals": 2, "awayGoals": 2, "pointsWon": 9, "appearances": 94, "subappearances": 0, "minsPlayed": 8501, "appearancesHome": 46, "appearancesAway": 48, "subappearancesHome": 7, "subappearancesAway": 8, "minsPlayedHome": 4159, "minsPlayedAway": 4342}]}