{"name": "Alf-Inge H\u00e5land", "events": [{"player": {"name": "Alf-Inge H\u00e5land"}, "time": 65, "matchID": 8391, "season": 2000, "leagueID": 1000, "leaguename": "English Premier League", "type": "goal", "teamFor": "Manchester City", "teamAgainst": "Aston Villa", "venueStatus": "A", "goalType": "", "assistBy": "", "teamForScore": 1, "teamAgainstScore": 0, "gameStatus": "W"}, {"player": {"name": "Alf-Inge H\u00e5land"}, "time": 23, "matchID": 8238, "season": 2000, "leagueID": 1000, "leaguename": "English Premier League", "type": "goal", "teamFor": "Manchester City", "teamAgainst": "Sunderland AFC", "venueStatus": "H", "goalType": "", "assistBy": "", "teamForScore": 2, "teamAgainstScore": 0, "gameStatus": "W+"}, {"player": {"name": "Alf-Inge H\u00e5land"}, "time": 45, "matchID": 8305, "season": 2000, "leagueID": 1000, "leaguename": "English Premier League", "type": "goal", "teamFor": "Manchester City", "teamAgainst": "Bradford City", "venueStatus": "H", "goalType": "", "assistBy": "", "teamForScore": 2, "teamAgainstScore": 0, "gameStatus": "W+"}], "id": 2379, "clubStats": [{"club": "Manchester City", "goals": 3, "owngoals": 0, "penalties": 0, "assists": 0, "gcGoal": 1, "gcAssists": 0, "homeGoals": 2, "awayGoals": 1, "pointsWon": 0, "appearances": 33, "subappearances": 0, "minsPlayed": 2862, "appearancesHome": 17, "appearancesAway": 16, "subappearancesHome": 0, "subappearancesAway": 0, "minsPlayedHome": 1450, "minsPlayedAway": 1412}, {"club": "West Ham United", "goals": 0, "owngoals": 0, "penalties": 0, "assists": 0, "gcGoal": 0, "gcAssists": 0, "homeGoals": 0, "awayGoals": 0, "pointsWon": 0, "appearances": 1, "subappearances": 0, "minsPlayed": 90, "appearancesHome": 1, "appearancesAway": 0, "subappearancesHome": 0, "subappearancesAway": 0, "minsPlayedHome": 90, "minsPlayedAway": 0}]}