{"name": "Carlos Marinelli", "events": [{"player": {"name": "Carlos Marinelli"}, "time": 57, "matchID": 7954, "season": 2001, "leagueID": 1000, "leaguename": "English Premier League", "type": "goal", "teamFor": "Middlesbrough FC", "teamAgainst": "Derby County", "venueStatus": "H", "goalType": "", "assistBy": "", "teamForScore": 2, "teamAgainstScore": 0, "gameStatus": "W+"}, {"player": {"name": "Carlos Marinelli"}, "time": 82, "matchID": 7954, "season": 2001, "leagueID": 1000, "leaguename": "English Premier League", "type": "goal", "teamFor": "Middlesbrough FC", "teamAgainst": "Derby County", "venueStatus": "H", "goalType": "", "assistBy": "", "teamForScore": 5, "teamAgainstScore": 0, "gameStatus": "W+"}, {"player": {"name": "Carlos Marinelli"}, "time": 9, "matchID": 7085, "season": 2003, "leagueID": 1000, "leaguename": "English Premier League", "type": "goal", "teamFor": "Middlesbrough FC", "teamAgainst": "Fulham FC", "venueStatus": "A", "goalType": "", "assistBy": "", "teamForScore": 1, "teamAgainstScore": 0, "gameStatus": "W"}], "id": 2435, "clubStats": [{"club": "Middlesbrough FC", "goals": 3, "owngoals": 0, "penalties": 0, "assists": 0, "gcGoal": 1, "gcAssists": 0, "homeGoals": 2, "awayGoals": 1, "pointsWon": 0, "appearances": 18, "subappearances": 0, "minsPlayed": 1865, "appearancesHome": 10, "appearancesAway": 8, "subappearancesHome": 10, "subappearancesAway": 13, "minsPlayedHome": 991, "minsPlayedAway": 874}]}