{"name": "Gary Medel", "events": [{"player": {"name": "Gary Medel"}, "time": 73, "matchID": 3592, "season": 2013, "leagueID": 1000, "leaguename": "English Premier League", "type": "assist", "teamFor": "Cardiff City", "teamAgainst": "West Bromwich Albion", "venueStatus": "A", "goalType": "", "goalBy": "Steven Caulker", "teamForScore": 2, "teamAgainstScore": 2}], "id": 3030, "clubStats": [{"club": "Cardiff City", "goals": 0, "owngoals": 0, "penalties": 0, "assists": 1, "gcGoal": 0, "gcAssists": 0, "homeGoals": 0, "awayGoals": 0, "pointsWon": 0, "appearances": 34, "subappearances": 0, "minsPlayed": 2870, "appearancesHome": 16, "appearancesAway": 18, "subappearancesHome": 0, "subappearancesAway": 0, "minsPlayedHome": 1398, "minsPlayedAway": 1472}]}