{"name": "Stewart Downing", "events": [{"player": {"name": "Stewart Downing"}, "time": 28, "matchID": 4537, "season": 2010, "leagueID": 1000, "leaguename": "English Premier League", "type": "goal", "teamFor": "Aston Villa", "teamAgainst": "Blackpool FC", "venueStatus": "H", "goalType": "", "assistBy": "Ashley Young", "teamForScore": 1, "teamAgainstScore": 0, "gameStatus": "W"}, {"player": {"name": "Stewart Downing"}, "time": 87, "matchID": 4537, "season": 2010, "leagueID": 1000, "leaguename": "English Premier League", "type": "assist", "teamFor": "Aston Villa", "teamAgainst": "Blackpool FC", "venueStatus": "H", "goalType": "", "goalBy": "James Collins", "teamForScore": 3, "teamAgainstScore": 2}, {"player": {"name": "Stewart Downing"}, "time": 38, "matchID": 2175, "season": 2016, "leagueID": 1000, "leaguename": "English Premier League", "type": "assist", "teamFor": "Middlesbrough FC", "teamAgainst": "Crystal Palace", "venueStatus": "H", "goalType": "header", "goalBy": "Daniel Ayala", "teamForScore": 1, "teamAgainstScore": 1}, {"player": {"name": "Stewart Downing"}, "time": 37, "matchID": 5604, "season": 2007, "leagueID": 1000, "leaguename": "English Premier League", "type": "goal", "teamFor": "Middlesbrough FC", "teamAgainst": "Birmingham City", "venueStatus": "H", "goalType": "", "assistBy": "George Boateng", "teamForScore": 2, "teamAgainstScore": 0, "gameStatus": "W+"}, {"player": {"name": "Stewart Downing"}, "time": 37, "matchID": 2913, "season": 2014, "leagueID": 1000, "leaguename": "English Premier League", "type": "goal", "teamFor": "West Ham United", "teamAgainst": "Crystal Palace", "venueStatus": "A", "goalType": "left-footed shot", "assistBy": "Cheikhou Kouyat\u00e9", "teamForScore": 2, "teamAgainstScore": 0, "gameStatus": "W+"}, {"player": {"name": "Stewart Downing"}, "time": 52, "matchID": 5925, "season": 2007, "leagueID": 1000, "leaguename": "English Premier League", "type": "assist", "teamFor": "Middlesbrough FC", "teamAgainst": "Portsmouth FC", "venueStatus": "H", "goalType": "header", "goalBy": "Tuncay \u015eanl\u0131", "teamForScore": 2, "teamAgainstScore": 0}, {"player": {"name": "Stewart Downing"}, "time": 44, "matchID": 3641, "season": 2013, "leagueID": 1000, "leaguename": "English Premier League", "type": "goal", "teamFor": "West Ham United", "teamAgainst": "Tottenham Hotspur", "venueStatus": "H", "goalType": "", "assistBy": "", "teamForScore": 2, "teamAgainstScore": 0, "gameStatus": "W+"}, {"player": {"name": "Stewart Downing"}, "time": 45, "matchID": 6288, "season": 2006, "leagueID": 1000, "leaguename": "English Premier League", "type": "assist", "teamFor": "Middlesbrough FC", "teamAgainst": "Manchester United", "venueStatus": "A", "goalType": "", "goalBy": "Mark Viduka", "teamForScore": 1, "teamAgainstScore": 1}, {"player": {"name": "Stewart Downing"}, "time": 23, "matchID": 5847, "season": 2007, "leagueID": 1000, "leaguename": "English Premier League", "type": "goal", "teamFor": "Middlesbrough FC", "teamAgainst": "Aston Villa", "venueStatus": "A", "goalType": "left-footed shot", "assistBy": "", "teamForScore": 1, "teamAgainstScore": 0, "gameStatus": "W"}, {"player": {"name": "Stewart Downing"}, "time": 74, "matchID": 4006, "season": 2012, "leagueID": 1000, "leaguename": "English Premier League", "type": "assist", "teamFor": "Liverpool FC", "teamAgainst": "Newcastle United", "venueStatus": "A", "goalType": "right-footed shot", "goalBy": "Fabio Borini", "teamForScore": 5, "teamAgainstScore": 0}, {"player": {"name": "Stewart Downing"}, "time": 38, "matchID": 5722, "season": 2007, "leagueID": 1000, "leaguename": "English Premier League", "type": "assist", "teamFor": "Middlesbrough FC", "teamAgainst": "Derby County", "venueStatus": "A", "goalType": "left-footed shot", "goalBy": "Tuncay \u015eanl\u0131", "teamForScore": 1, "teamAgainstScore": 0}, {"player": {"name": "Stewart Downing"}, "time": 69, "matchID": 5896, "season": 2007, "leagueID": 1000, "leaguename": "English Premier League", "type": "goal", "teamFor": "Middlesbrough FC", "teamAgainst": "Tottenham Hotspur", "venueStatus": "A", "goalType": "right-footed shot", "assistBy": "", "teamForScore": 1, "teamAgainstScore": 1, "gameStatus": "D"}, {"player": {"name": "Stewart Downing"}, "time": 59, "matchID": 3881, "season": 2012, "leagueID": 1000, "leaguename": "English Premier League", "type": "assist", "teamFor": "Liverpool FC", "teamAgainst": "Norwich City", "venueStatus": "H", "goalType": "", "goalBy": "Daniel Sturridge", "teamForScore": 3, "teamAgainstScore": 0}, {"player": {"name": "Stewart Downing"}, "time": 50, "matchID": 2470, "season": 2016, "leagueID": 1000, "leaguename": "English Premier League", "type": "assist", "teamFor": "Middlesbrough FC", "teamAgainst": "Arsenal FC", "venueStatus": "H", "goalType": "left-footed shot", "goalBy": "\u00c1lvaro Negredo", "teamForScore": 1, "teamAgainstScore": 1}, {"player": {"name": "Stewart Downing"}, "time": 26, "matchID": 4583, "season": 2010, "leagueID": 1000, "leaguename": "English Premier League", "type": "goal", "teamFor": "Aston Villa", "teamAgainst": "West Bromwich Albion", "venueStatus": "H", "goalType": "", "assistBy": "Ashley Young", "teamForScore": 1, "teamAgainstScore": 0, "gameStatus": "W"}, {"player": {"name": "Stewart Downing"}, "time": 45, "matchID": 3036, "season": 2014, "leagueID": 1000, "leaguename": "English Premier League", "type": "assist", "teamFor": "West Ham United", "teamAgainst": "West Bromwich Albion", "venueStatus": "A", "goalType": "", "goalBy": "James Tomkins", "teamForScore": 2, "teamAgainstScore": 1}, {"player": {"name": "Stewart Downing"}, "time": 82, "matchID": 3405, "season": 2013, "leagueID": 1000, "leaguename": "English Premier League", "type": "assist", "teamFor": "West Ham United", "teamAgainst": "Fulham FC", "venueStatus": "H", "goalType": "", "goalBy": "Carlton Cole", "teamForScore": 2, "teamAgainstScore": 0}, {"player": {"name": "Stewart Downing"}, "time": 15, "matchID": 5935, "season": 2007, "leagueID": 1000, "leaguename": "English Premier League", "type": "goal", "teamFor": "Middlesbrough FC", "teamAgainst": "Manchester City", "venueStatus": "H", "goalType": "penalty", "assistBy": "", "teamForScore": 1, "teamAgainstScore": 0, "gameStatus": "W"}, {"player": {"name": "Stewart Downing"}, "time": 58, "matchID": 5935, "season": 2007, "leagueID": 1000, "leaguename": "English Premier League", "type": "goal", "teamFor": "Middlesbrough FC", "teamAgainst": "Manchester City", "venueStatus": "H", "goalType": "left-footed shot", "assistBy": "", "teamForScore": 3, "teamAgainstScore": 0, "gameStatus": "W+"}, {"player": {"name": "Stewart Downing"}, "time": 66, "matchID": 3946, "season": 2012, "leagueID": 1000, "leaguename": "English Premier League", "type": "goal", "teamFor": "Liverpool FC", "teamAgainst": "Tottenham Hotspur", "venueStatus": "H", "goalType": "right-footed shot", "assistBy": "", "teamForScore": 2, "teamAgainstScore": 2, "gameStatus": "D"}, {"player": {"name": "Stewart Downing"}, "time": 10, "matchID": 6173, "season": 2006, "leagueID": 1000, "leaguename": "English Premier League", "type": "assist", "teamFor": "Middlesbrough FC", "teamAgainst": "Bolton Wanderers", "venueStatus": "H", "goalType": "header", "goalBy": "Abel Xavier", "teamForScore": 2, "teamAgainstScore": 0}, {"player": {"name": "Stewart Downing"}, "time": 23, "matchID": 6173, "season": 2006, "leagueID": 1000, "leaguename": "English Premier League", "type": "assist", "teamFor": "Middlesbrough FC", "teamAgainst": "Bolton Wanderers", "venueStatus": "H", "goalType": "right-footed shot", "goalBy": "Mark Viduka", "teamForScore": 3, "teamAgainstScore": 0}, {"player": {"name": "Stewart Downing"}, "time": 43, "matchID": 6173, "season": 2006, "leagueID": 1000, "leaguename": "English Premier League", "type": "goal", "teamFor": "Middlesbrough FC", "teamAgainst": "Bolton Wanderers", "venueStatus": "H", "goalType": "right-footed shot", "assistBy": "George Boateng", "teamForScore": 4, "teamAgainstScore": 1, "gameStatus": "W+"}, {"player": {"name": "Stewart Downing"}, "time": 43, "matchID": 3106, "season": 2014, "leagueID": 1000, "leaguename": "English Premier League", "type": "assist", "teamFor": "West Ham United", "teamAgainst": "Swansea City", "venueStatus": "A", "goalType": "left-footed shot", "goalBy": "Andy Carroll", "teamForScore": 1, "teamAgainstScore": 0}, {"player": {"name": "Stewart Downing"}, "time": 56, "matchID": 5067, "season": 2009, "leagueID": 1000, "leaguename": "English Premier League", "type": "goal", "teamFor": "Aston Villa", "teamAgainst": "Burnley FC", "venueStatus": "H", "goalType": "right-footed shot", "assistBy": "Ashley Young", "teamForScore": 2, "teamAgainstScore": 1, "gameStatus": "W"}, {"player": {"name": "Stewart Downing"}, "time": 58, "matchID": 5067, "season": 2009, "leagueID": 1000, "leaguename": "English Premier League", "type": "goal", "teamFor": "Aston Villa", "teamAgainst": "Burnley FC", "venueStatus": "H", "goalType": "left-footed shot", "assistBy": "James Milner", "teamForScore": 3, "teamAgainstScore": 1, "gameStatus": "W+"}, {"player": {"name": "Stewart Downing"}, "time": 46, "matchID": 3522, "season": 2013, "leagueID": 1000, "leaguename": "English Premier League", "type": "assist", "teamFor": "West Ham United", "teamAgainst": "Aston Villa", "venueStatus": "A", "goalType": "", "goalBy": "Kevin Nolan", "teamForScore": 1, "teamAgainstScore": 0}, {"player": {"name": "Stewart Downing"}, "time": 89, "matchID": 5243, "season": 2008, "leagueID": 1000, "leaguename": "English Premier League", "type": "assist", "teamFor": "Middlesbrough FC", "teamAgainst": "Wigan Athletic", "venueStatus": "A", "goalType": "left-footed shot", "goalBy": "J\u00e9r\u00e9mie Aliadi\u00e9re", "teamForScore": 1, "teamAgainstScore": 0}, {"player": {"name": "Stewart Downing"}, "time": 56, "matchID": 3067, "season": 2014, "leagueID": 1000, "leaguename": "English Premier League", "type": "goal", "teamFor": "West Ham United", "teamAgainst": "Leicester City", "venueStatus": "H", "goalType": "", "assistBy": "Diafra Sakho", "teamForScore": 2, "teamAgainstScore": 0, "gameStatus": "W+"}, {"player": {"name": "Stewart Downing"}, "time": 25, "matchID": 4479, "season": 2010, "leagueID": 1000, "leaguename": "English Premier League", "type": "goal", "teamFor": "Aston Villa", "teamAgainst": "Wolverhampton Wanderers", "venueStatus": "A", "goalType": "", "assistBy": "Marc Albrighton", "teamForScore": 1, "teamAgainstScore": 0, "gameStatus": "W"}, {"player": {"name": "Stewart Downing"}, "time": 15, "matchID": 4425, "season": 2010, "leagueID": 1000, "leaguename": "English Premier League", "type": "goal", "teamFor": "Aston Villa", "teamAgainst": "West Ham United", "venueStatus": "H", "goalType": "", "assistBy": "Marc Albrighton", "teamForScore": 1, "teamAgainstScore": 0, "gameStatus": "W"}, {"player": {"name": "Stewart Downing"}, "time": 60, "matchID": 2997, "season": 2014, "leagueID": 1000, "leaguename": "English Premier League", "type": "assist", "teamFor": "West Ham United", "teamAgainst": "Stoke City", "venueStatus": "A", "goalType": "", "goalBy": "Enner Valencia", "teamForScore": 1, "teamAgainstScore": 2}, {"player": {"name": "Stewart Downing"}, "time": 73, "matchID": 2997, "season": 2014, "leagueID": 1000, "leaguename": "English Premier League", "type": "goal", "teamFor": "West Ham United", "teamAgainst": "Stoke City", "venueStatus": "A", "goalType": "", "assistBy": "Enner Valencia", "teamForScore": 2, "teamAgainstScore": 2, "gameStatus": "D"}, {"player": {"name": "Stewart Downing"}, "time": 12, "matchID": 5782, "season": 2007, "leagueID": 1000, "leaguename": "English Premier League", "type": "assist", "teamFor": "Middlesbrough FC", "teamAgainst": "Blackburn Rovers", "venueStatus": "A", "goalType": "header", "goalBy": "David Wheater", "teamForScore": 1, "teamAgainstScore": 0}, {"player": {"name": "Stewart Downing"}, "time": 56, "matchID": 2233, "season": 2016, "leagueID": 1000, "leaguename": "English Premier League", "type": "goal", "teamFor": "Middlesbrough FC", "teamAgainst": "AFC Bournemouth", "venueStatus": "H", "goalType": "right-footed shot", "assistBy": "\u00c1lvaro Negredo", "teamForScore": 2, "teamAgainstScore": 0, "gameStatus": "W+"}, {"player": {"name": "Stewart Downing"}, "time": 64, "matchID": 4705, "season": 2010, "leagueID": 1000, "leaguename": "English Premier League", "type": "assist", "teamFor": "Aston Villa", "teamAgainst": "Bolton Wanderers", "venueStatus": "A", "goalType": "right-footed shot", "goalBy": "Marc Albrighton", "teamForScore": 2, "teamAgainstScore": 1}, {"player": {"name": "Stewart Downing"}, "time": 76, "matchID": 3161, "season": 2014, "leagueID": 1000, "leaguename": "English Premier League", "type": "assist", "teamFor": "West Ham United", "teamAgainst": "Crystal Palace", "venueStatus": "H", "goalType": "right-footed shot", "goalBy": "Enner Valencia", "teamForScore": 1, "teamAgainstScore": 3}, {"player": {"name": "Stewart Downing"}, "time": 16, "matchID": 5162, "season": 2009, "leagueID": 1000, "leaguename": "English Premier League", "type": "assist", "teamFor": "Aston Villa", "teamAgainst": "Manchester City", "venueStatus": "A", "goalType": "right-footed shot", "goalBy": "John Carew", "teamForScore": 1, "teamAgainstScore": 0}, {"player": {"name": "Stewart Downing"}, "time": 8, "matchID": 5309, "season": 2008, "leagueID": 1000, "leaguename": "English Premier League", "type": "assist", "teamFor": "Middlesbrough FC", "teamAgainst": "Everton FC", "venueStatus": "A", "goalType": "", "goalBy": "Gary O'Neil", "teamForScore": 1, "teamAgainstScore": 0}, {"player": {"name": "Stewart Downing"}, "time": 33, "matchID": 6778, "season": 2004, "leagueID": 1000, "leaguename": "English Premier League", "type": "goal", "teamFor": "Middlesbrough FC", "teamAgainst": "Manchester United", "venueStatus": "A", "goalType": "", "assistBy": "", "teamForScore": 1, "teamAgainstScore": 0, "gameStatus": "W"}, {"player": {"name": "Stewart Downing"}, "time": 3, "matchID": 5717, "season": 2007, "leagueID": 1000, "leaguename": "English Premier League", "type": "goal", "teamFor": "Middlesbrough FC", "teamAgainst": "Arsenal FC", "venueStatus": "H", "goalType": "penalty", "assistBy": "", "teamForScore": 1, "teamAgainstScore": 0, "gameStatus": "W"}, {"player": {"name": "Stewart Downing"}, "time": 65, "matchID": 2194, "season": 2016, "leagueID": 1000, "leaguename": "English Premier League", "type": "assist", "teamFor": "Middlesbrough FC", "teamAgainst": "Tottenham Hotspur", "venueStatus": "H", "goalType": "header", "goalBy": "Ben Gibson", "teamForScore": 1, "teamAgainstScore": 2}, {"player": {"name": "Stewart Downing"}, "time": 64, "matchID": 4691, "season": 2010, "leagueID": 1000, "leaguename": "English Premier League", "type": "goal", "teamFor": "Aston Villa", "teamAgainst": "Blackburn Rovers", "venueStatus": "H", "goalType": "left-footed shot", "assistBy": "Ashley Young", "teamForScore": 3, "teamAgainstScore": 0, "gameStatus": "W+"}, {"player": {"name": "Stewart Downing"}, "time": 82, "matchID": 4691, "season": 2010, "leagueID": 1000, "leaguename": "English Premier League", "type": "assist", "teamFor": "Aston Villa", "teamAgainst": "Blackburn Rovers", "venueStatus": "H", "goalType": "right-footed shot", "goalBy": "Ashley Young", "teamForScore": 4, "teamAgainstScore": 1}, {"player": {"name": "Stewart Downing"}, "time": 56, "matchID": 3921, "season": 2012, "leagueID": 1000, "leaguename": "English Premier League", "type": "assist", "teamFor": "Liverpool FC", "teamAgainst": "Swansea City", "venueStatus": "H", "goalType": "", "goalBy": "Luis Su\u00e1rez", "teamForScore": 4, "teamAgainstScore": 0}, {"player": {"name": "Stewart Downing"}, "time": 74, "matchID": 6798, "season": 2004, "leagueID": 1000, "leaguename": "English Premier League", "type": "goal", "teamFor": "Middlesbrough FC", "teamAgainst": "Portsmouth FC", "venueStatus": "H", "goalType": "", "assistBy": "", "teamForScore": 1, "teamAgainstScore": 1, "gameStatus": "D"}, {"player": {"name": "Stewart Downing"}, "time": 36, "matchID": 3838, "season": 2012, "leagueID": 1000, "leaguename": "English Premier League", "type": "assist", "teamFor": "Liverpool FC", "teamAgainst": "Fulham FC", "venueStatus": "H", "goalType": "", "goalBy": "Steven Gerrard", "teamForScore": 2, "teamAgainstScore": 0}, {"player": {"name": "Stewart Downing"}, "time": 52, "matchID": 3838, "season": 2012, "leagueID": 1000, "leaguename": "English Premier League", "type": "goal", "teamFor": "Liverpool FC", "teamAgainst": "Fulham FC", "venueStatus": "H", "goalType": "", "assistBy": "Steven Gerrard", "teamForScore": 3, "teamAgainstScore": 0, "gameStatus": "W+"}, {"player": {"name": "Stewart Downing"}, "time": 5, "matchID": 6258, "season": 2006, "leagueID": 1000, "leaguename": "English Premier League", "type": "assist", "teamFor": "Middlesbrough FC", "teamAgainst": "Watford FC", "venueStatus": "H", "goalType": "", "goalBy": "Mark Viduka", "teamForScore": 1, "teamAgainstScore": 0}, {"player": {"name": "Stewart Downing"}, "time": 33, "matchID": 4792, "season": 2010, "leagueID": 1000, "leaguename": "English Premier League", "type": "goal", "teamFor": "Aston Villa", "teamAgainst": "Liverpool FC", "venueStatus": "H", "goalType": "left-footed shot", "assistBy": "Marc Albrighton", "teamForScore": 1, "teamAgainstScore": 0, "gameStatus": "W"}, {"player": {"name": "Stewart Downing"}, "time": 67, "matchID": 5623, "season": 2007, "leagueID": 1000, "leaguename": "English Premier League", "type": "goal", "teamFor": "Middlesbrough FC", "teamAgainst": "Sunderland AFC", "venueStatus": "H", "goalType": "right-footed shot", "assistBy": "", "teamForScore": 2, "teamAgainstScore": 1, "gameStatus": "W"}, {"player": {"name": "Stewart Downing"}, "time": 29, "matchID": 3055, "season": 2014, "leagueID": 1000, "leaguename": "English Premier League", "type": "goal", "teamFor": "West Ham United", "teamAgainst": "Sunderland AFC", "venueStatus": "A", "goalType": "", "assistBy": "Kevin Nolan", "teamForScore": 1, "teamAgainstScore": 1, "gameStatus": "D"}, {"player": {"name": "Stewart Downing"}, "time": 90, "matchID": 6866, "season": 2004, "leagueID": 1000, "leaguename": "English Premier League", "type": "goal", "teamFor": "Middlesbrough FC", "teamAgainst": "Southampton FC", "venueStatus": "A", "goalType": "", "assistBy": "", "teamForScore": 2, "teamAgainstScore": 2, "gameStatus": "D"}, {"player": {"name": "Stewart Downing"}, "time": 9, "matchID": 5823, "season": 2007, "leagueID": 1000, "leaguename": "English Premier League", "type": "assist", "teamFor": "Middlesbrough FC", "teamAgainst": "Liverpool FC", "venueStatus": "A", "goalType": "header", "goalBy": "Tuncay \u015eanl\u0131", "teamForScore": 1, "teamAgainstScore": 0}, {"player": {"name": "Stewart Downing"}, "time": 83, "matchID": 5823, "season": 2007, "leagueID": 1000, "leaguename": "English Premier League", "type": "goal", "teamFor": "Middlesbrough FC", "teamAgainst": "Liverpool FC", "venueStatus": "A", "goalType": "left-footed shot", "assistBy": "Julio Arca", "teamForScore": 2, "teamAgainstScore": 3, "gameStatus": "L"}, {"player": {"name": "Stewart Downing"}, "time": 50, "matchID": 2940, "season": 2014, "leagueID": 1000, "leaguename": "English Premier League", "type": "assist", "teamFor": "West Ham United", "teamAgainst": "Hull City", "venueStatus": "A", "goalType": "right-footed shot", "goalBy": "Enner Valencia", "teamForScore": 1, "teamAgainstScore": 1}, {"player": {"name": "Stewart Downing"}, "time": 67, "matchID": 2940, "season": 2014, "leagueID": 1000, "leaguename": "English Premier League", "type": "assist", "teamFor": "West Ham United", "teamAgainst": "Hull City", "venueStatus": "A", "goalType": "right-footed shot", "goalBy": "Diafra Sakho", "teamForScore": 2, "teamAgainstScore": 2}, {"player": {"name": "Stewart Downing"}, "time": 11, "matchID": 5946, "season": 2006, "leagueID": 1000, "leaguename": "English Premier League", "type": "goal", "teamFor": "Middlesbrough FC", "teamAgainst": "Reading FC", "venueStatus": "A", "goalType": "", "assistBy": "", "teamForScore": 1, "teamAgainstScore": 0, "gameStatus": "W"}, {"player": {"name": "Stewart Downing"}, "time": 14, "matchID": 5544, "season": 2008, "leagueID": 1000, "leaguename": "English Premier League", "type": "assist", "teamFor": "Middlesbrough FC", "teamAgainst": "Aston Villa", "venueStatus": "H", "goalType": "right-footed shot", "goalBy": "Tuncay \u015eanl\u0131", "teamForScore": 1, "teamAgainstScore": 0}, {"player": {"name": "Stewart Downing"}, "time": 52, "matchID": 3999, "season": 2012, "leagueID": 1000, "leaguename": "English Premier League", "type": "assist", "teamFor": "Liverpool FC", "teamAgainst": "Chelsea FC", "venueStatus": "H", "goalType": "left-footed shot", "goalBy": "Daniel Sturridge", "teamForScore": 1, "teamAgainstScore": 1}, {"player": {"name": "Stewart Downing"}, "time": 35, "matchID": 4460, "season": 2010, "leagueID": 1000, "leaguename": "English Premier League", "type": "goal", "teamFor": "Aston Villa", "teamAgainst": "Stoke City", "venueStatus": "A", "goalType": "", "assistBy": "Gabriel Agbonlahor", "teamForScore": 1, "teamAgainstScore": 0, "gameStatus": "W"}, {"player": {"name": "Stewart Downing"}, "time": 31, "matchID": 5565, "season": 2007, "leagueID": 1000, "leaguename": "English Premier League", "type": "goal", "teamFor": "Middlesbrough FC", "teamAgainst": "Blackburn Rovers", "venueStatus": "H", "goalType": "free kick", "assistBy": "", "teamForScore": 1, "teamAgainstScore": 0, "gameStatus": "W"}, {"player": {"name": "Stewart Downing"}, "time": 19, "matchID": 5794, "season": 2007, "leagueID": 1000, "leaguename": "English Premier League", "type": "assist", "teamFor": "Middlesbrough FC", "teamAgainst": "Wigan Athletic", "venueStatus": "H", "goalType": "right-footed shot", "goalBy": "J\u00e9r\u00e9mie Aliadi\u00e9re", "teamForScore": 1, "teamAgainstScore": 0}, {"player": {"name": "Stewart Downing"}, "time": 66, "matchID": 6297, "season": 2006, "leagueID": 1000, "leaguename": "English Premier League", "type": "assist", "teamFor": "Middlesbrough FC", "teamAgainst": "Tottenham Hotspur", "venueStatus": "H", "goalType": "header", "goalBy": "Mark Viduka", "teamForScore": 1, "teamAgainstScore": 2}, {"player": {"name": "Stewart Downing"}, "time": 89, "matchID": 6297, "season": 2006, "leagueID": 1000, "leaguename": "English Premier League", "type": "assist", "teamFor": "Middlesbrough FC", "teamAgainst": "Tottenham Hotspur", "venueStatus": "H", "goalType": "header", "goalBy": "Emanuel Pogatetz", "teamForScore": 2, "teamAgainstScore": 3}, {"player": {"name": "Stewart Downing"}, "time": 59, "matchID": 4663, "season": 2010, "leagueID": 1000, "leaguename": "English Premier League", "type": "assist", "teamFor": "Aston Villa", "teamAgainst": "Manchester United", "venueStatus": "A", "goalType": "left-footed shot", "goalBy": "Darren Bent", "teamForScore": 1, "teamAgainstScore": 2}, {"player": {"name": "Stewart Downing"}, "time": 88, "matchID": 2946, "season": 2014, "leagueID": 1000, "leaguename": "English Premier League", "type": "assist", "teamFor": "West Ham United", "teamAgainst": "Liverpool FC", "venueStatus": "H", "goalType": "right-footed shot", "goalBy": "Morgan Amalfitano", "teamForScore": 3, "teamAgainstScore": 1}, {"player": {"name": "Stewart Downing"}, "time": 47, "matchID": 4629, "season": 2010, "leagueID": 1000, "leaguename": "English Premier League", "type": "assist", "teamFor": "Aston Villa", "teamAgainst": "Chelsea FC", "venueStatus": "A", "goalType": "header", "goalBy": "Emile Heskey", "teamForScore": 2, "teamAgainstScore": 1}, {"player": {"name": "Stewart Downing"}, "time": 73, "matchID": 6708, "season": 2004, "leagueID": 1000, "leaguename": "English Premier League", "type": "goal", "teamFor": "Middlesbrough FC", "teamAgainst": "Newcastle United", "venueStatus": "H", "goalType": "", "assistBy": "", "teamForScore": 1, "teamAgainstScore": 1, "gameStatus": "D"}, {"player": {"name": "Stewart Downing"}, "time": 21, "matchID": 5744, "season": 2007, "leagueID": 1000, "leaguename": "English Premier League", "type": "goal", "teamFor": "Birmingham City", "teamAgainst": "Middlesbrough FC", "venueStatus": "H", "goalType": "own goal", "assistBy": "", "teamForScore": 1, "teamAgainstScore": 0}, {"player": {"name": "Stewart Downing"}, "time": 90, "matchID": 7046, "season": 2004, "leagueID": 1000, "leaguename": "English Premier League", "type": "goal", "teamFor": "Middlesbrough FC", "teamAgainst": "West Bromwich Albion", "venueStatus": "H", "goalType": "", "assistBy": "", "teamForScore": 4, "teamAgainstScore": 0, "gameStatus": "W+"}, {"player": {"name": "Stewart Downing"}, "time": 2, "matchID": 3938, "season": 2012, "leagueID": 1000, "leaguename": "English Premier League", "type": "goal", "teamFor": "Liverpool FC", "teamAgainst": "Wigan Athletic", "venueStatus": "A", "goalType": "header", "assistBy": "Coutinho", "teamForScore": 1, "teamAgainstScore": 0, "gameStatus": "W"}, {"player": {"name": "Stewart Downing"}, "time": 45, "matchID": 6576, "season": 2005, "leagueID": 1000, "leaguename": "English Premier League", "type": "goal", "teamFor": "Middlesbrough FC", "teamAgainst": "Chelsea FC", "venueStatus": "H", "goalType": "", "assistBy": "", "teamForScore": 2, "teamAgainstScore": 0, "gameStatus": "W+"}, {"player": {"name": "Stewart Downing"}, "time": 89, "matchID": 6307, "season": 2006, "leagueID": 1000, "leaguename": "English Premier League", "type": "assist", "teamFor": "Middlesbrough FC", "teamAgainst": "Wigan Athletic", "venueStatus": "A", "goalType": "", "goalBy": "Mark Viduka", "teamForScore": 1, "teamAgainstScore": 0}, {"player": {"name": "Stewart Downing"}, "time": 62, "matchID": 3266, "season": 2014, "leagueID": 1000, "leaguename": "English Premier League", "type": "goal", "teamFor": "West Ham United", "teamAgainst": "Everton FC", "venueStatus": "H", "goalType": "left-footed shot", "assistBy": "Alex Song", "teamForScore": 1, "teamAgainstScore": 0, "gameStatus": "W"}, {"player": {"name": "Stewart Downing"}, "time": 47, "matchID": 4722, "season": 2010, "leagueID": 1000, "leaguename": "English Premier League", "type": "assist", "teamFor": "Aston Villa", "teamAgainst": "Everton FC", "venueStatus": "A", "goalType": "", "goalBy": "Darren Bent", "teamForScore": 1, "teamAgainstScore": 1}, {"player": {"name": "Stewart Downing"}, "time": 76, "matchID": 4541, "season": 2010, "leagueID": 1000, "leaguename": "English Premier League", "type": "assist", "teamFor": "Aston Villa", "teamAgainst": "Manchester United", "venueStatus": "H", "goalType": "right-footed shot", "goalBy": "Marc Albrighton", "teamForScore": 2, "teamAgainstScore": 0}, {"player": {"name": "Stewart Downing"}, "time": 66, "matchID": 3048, "season": 2014, "leagueID": 1000, "leaguename": "English Premier League", "type": "assist", "teamFor": "West Ham United", "teamAgainst": "Swansea City", "venueStatus": "H", "goalType": "", "goalBy": "Andy Carroll", "teamForScore": 2, "teamAgainstScore": 1}, {"player": {"name": "Stewart Downing"}, "time": 45, "matchID": 5384, "season": 2008, "leagueID": 1000, "leaguename": "English Premier League", "type": "assist", "teamFor": "Middlesbrough FC", "teamAgainst": "Sunderland AFC", "venueStatus": "H", "goalType": "", "goalBy": "Afonso Alves", "teamForScore": 1, "teamAgainstScore": 0}, {"player": {"name": "Stewart Downing"}, "time": 72, "matchID": 3118, "season": 2014, "leagueID": 1000, "leaguename": "English Premier League", "type": "goal", "teamFor": "West Ham United", "teamAgainst": "Hull City", "venueStatus": "H", "goalType": "left-footed shot", "assistBy": "Alex Song", "teamForScore": 3, "teamAgainstScore": 0, "gameStatus": "W+"}], "id": 1333, "clubStats": [{"club": "Aston Villa", "goals": 9, "owngoals": 0, "penalties": 0, "assists": 8, "gcGoal": 7, "gcAssists": 0, "homeGoals": 7, "awayGoals": 2, "pointsWon": 9, "appearances": 58, "subappearances": 0, "minsPlayed": 5193, "appearancesHome": 31, "appearancesAway": 27, "subappearancesHome": 0, "subappearancesAway": 2, "minsPlayedHome": 2735, "minsPlayedAway": 2458}, {"club": "Middlesbrough FC", "goals": 18, "owngoals": 1, "penalties": 2, "assists": 19, "gcGoal": 11, "gcAssists": 0, "homeGoals": 12, "awayGoals": 6, "pointsWon": 9, "appearances": 179, "subappearances": 0, "minsPlayed": 16454, "appearancesHome": 87, "appearancesAway": 92, "subappearancesHome": 21, "subappearancesAway": 9, "minsPlayedHome": 8180, "minsPlayedAway": 8274}, {"club": "West Ham United", "goals": 7, "owngoals": 0, "penalties": 0, "assists": 10, "gcGoal": 3, "gcAssists": 0, "homeGoals": 4, "awayGoals": 3, "pointsWon": 6, "appearances": 66, "subappearances": 0, "minsPlayed": 5826, "appearancesHome": 33, "appearancesAway": 33, "subappearancesHome": 1, "subappearancesAway": 2, "minsPlayedHome": 2951, "minsPlayedAway": 2875}, {"club": "Liverpool FC", "goals": 3, "owngoals": 0, "penalties": 0, "assists": 5, "gcGoal": 2, "gcAssists": 0, "homeGoals": 2, "awayGoals": 1, "pointsWon": 0, "appearances": 53, "subappearances": 0, "minsPlayed": 4669, "appearancesHome": 27, "appearancesAway": 26, "subappearancesHome": 5, "subappearancesAway": 7, "minsPlayedHome": 2364, "minsPlayedAway": 2305}, {"club": "Tottenham Hotspur", "goals": 0, "owngoals": 0, "penalties": 0, "assists": 0, "gcGoal": 0, "gcAssists": 0, "homeGoals": 0, "awayGoals": 0, "pointsWon": 0, "appearances": 1, "subappearances": 0, "minsPlayed": 87, "appearancesHome": 1, "appearancesAway": 0, "subappearancesHome": 0, "subappearancesAway": 0, "minsPlayedHome": 87, "minsPlayedAway": 0}, {"club": "Watford FC", "goals": 0, "owngoals": 0, "penalties": 0, "assists": 0, "gcGoal": 0, "gcAssists": 0, "homeGoals": 0, "awayGoals": 0, "pointsWon": 0, "appearances": 1, "subappearances": 0, "minsPlayed": 90, "appearancesHome": 1, "appearancesAway": 0, "subappearancesHome": 0, "subappearancesAway": 0, "minsPlayedHome": 90, "minsPlayedAway": 0}], "careerStats": [{"League": "English Premier League", "goals": 37, "owngoals": 1, "penalties": 2, "assists": 42, "gcGoal": 23, "gcAssists": 0, "homeGoals": 25, "awayGoals": 12, "pointsWon": 24, "appearances": 358, "subappearances": 0, "minsPlayed": 32319, "appearancesHome": 180, "appearancesAway": 178, "subappearancesHome": 27, "subappearancesAway": 20, "minsPlayedHome": 16407, "minsPlayedAway": 15912}]}